{
  "version": "1.1.1",
  "windows": {
    "main": {
      "main": true,
      "url": "app://editor/index.html",
      "windowType": "dockable",
      "x": -8,
      "y": -8,
      "width": 1456,
      "height": 876,
      "layout": {
        "children": [
          {
            "children": [
              {
                "active": 0,
                "children": [
                  "hierarchy"
                ],
                "height": 270.171875,
                "type": "panel",
                "width": 306
              },
              {
                "active": 0,
                "children": [
                  "assets",
                  "cloud-function"
                ],
                "height": 482.328125,
                "type": "panel",
                "width": 306
              }
            ],
            "height": 755.5,
            "type": "dock-v",
            "width": 306
          },
          {
            "children": [
              {
                "active": 0,
                "children": [
                  "scene"
                ],
                "height": 486.5,
                "type": "panel",
                "width": 818.984375
              },
              {
                "active": 0,
                "children": [
                  "console",
                  "timeline",
                  "game-window"
                ],
                "height": 266,
                "type": "panel",
                "width": 818.984375
              }
            ],
            "height": 755.5,
            "type": "dock-v",
            "width": 818.984375
          },
          {
            "active": 0,
            "children": [
              "inspector",
              "cocos-services"
            ],
            "height": 755.5,
            "type": "panel",
            "width": 309
          }
        ],
        "type": "dock-h"
      },
      "panels": [
        "hierarchy",
        "assets",
        "cloud-function",
        "scene",
        "console",
        "timeline",
        "game-window",
        "inspector",
        "cocos-services"
      ]
    }
  },
  "panels": {
    "builder": {
      "x": 508,
      "y": 28,
      "width": 516,
      "height": 740
    },
    "project-settings": {
      "x": 2408,
      "y": 256,
      "width": 604,
      "height": 568
    }
  },
  "panelLabelWidth": {
    "builder": null,
    "inspector": null,
    "project-settings": null
  }
}
