{
  "version": "1.1.1",
  "windows": {
    "main": {
      "main": true,
      "url": "app://editor/index.html",
      "windowType": "dockable",
      "x": 1913,
      "y": 0,
      "width": 1166,
      "height": 1047,
      "layout": {
        "children": [
          {
            "children": [
              {
                "active": 0,
                "children": [
                  "hierarchy"
                ],
                "height": 335.171875,
                "type": "panel",
                "width": 242
              },
              {
                "active": 0,
                "children": [
                  "assets",
                  "cloud-function"
                ],
                "height": 588.3125,
                "type": "panel",
                "width": 242
              }
            ],
            "height": 926.5,
            "type": "dock-v",
            "width": 242
          },
          {
            "children": [
              {
                "active": 0,
                "children": [
                  "scene"
                ],
                "height": 657.359375,
                "type": "panel",
                "width": 563
              },
              {
                "active": 0,
                "children": [
                  "console",
                  "timeline",
                  "game-window"
                ],
                "height": 266.140625,
                "type": "panel",
                "width": 563
              }
            ],
            "height": 926.5,
            "type": "dock-v",
            "width": 563
          },
          {
            "active": 0,
            "children": [
              "inspector",
              "cocos-services"
            ],
            "height": 926.5,
            "type": "panel",
            "width": 339
          }
        ],
        "type": "dock-h"
      },
      "panels": [
        "hierarchy",
        "assets",
        "cloud-function",
        "scene",
        "console",
        "timeline",
        "game-window",
        "inspector",
        "cocos-services"
      ]
    },
    "worker": {}
  },
  "panels": {
    "builder": {
      "x": 508,
      "y": 28,
      "width": 516,
      "height": 740
    },
    "project-settings": {
      "x": 2408,
      "y": 256,
      "width": 604,
      "height": 568
    }
  },
  "panelLabelWidth": {
    "builder": null,
    "inspector": null,
    "project-settings": null
  }
}
